fmu/__init__.py
fmu/tools/__init__.py
fmu/tools/_common.py
fmu/tools/extract_grid_zone_tops_etc.py
fmu/tools/version.py
fmu/tools/domainconversion/__init__.py
fmu/tools/domainconversion/dconvert.py
fmu/tools/ensembles/__init__.py
fmu/tools/ensembles/ensemble_well_props.py
fmu/tools/fipmapper/__init__.py
fmu/tools/fipmapper/fipmapper.py
fmu/tools/properties/__init__.py
fmu/tools/properties/swfunction.py
fmu/tools/qcdata/__init__.py
fmu/tools/qcdata/qcdata.py
fmu/tools/qcforward/__init__.py
fmu/tools/qcforward/_blockedwells_vs_gridprops.py
fmu/tools/qcforward/_grid_quality.py
fmu/tools/qcforward/_grid_statistics.py
fmu/tools/qcforward/_qcforward.py
fmu/tools/qcforward/_wellzonation_vs_grid.py
fmu/tools/qcforward/qcforward.py
fmu/tools/qcforward/_schemas/bw_vs_gridprops_asfile.json
fmu/tools/qcforward/_schemas/bw_vs_gridprops_asroxapi.json
fmu/tools/qcforward/_schemas/gridquality_asfile.json
fmu/tools/qcforward/_schemas/gridquality_asroxapi.json
fmu/tools/qcforward/_schemas/wellzonation_vs_grid_asfile.json
fmu/tools/qcforward/_schemas/wellzonation_vs_grid_asroxapi.json
fmu/tools/qcproperties/_aggregate_df.py
fmu/tools/qcproperties/_config_parser.py
fmu/tools/qcproperties/_grid2df.py
fmu/tools/qcproperties/_utils.py
fmu/tools/qcproperties/_well2df.py
fmu/tools/qcproperties/qcproperties.py
fmu/tools/rms/__init__.py
fmu/tools/rms/copy_rms_param_to_ertbox_grid.py
fmu/tools/rms/create_rft_ertobs.py
fmu/tools/rms/generate_bw_per_facies.py
fmu/tools/rms/generate_petro_jobs_for_field_update.py
fmu/tools/rms/import_localmodules.py
fmu/tools/rms/qcreset.py
fmu/tools/rms/rename_rms_scripts.py
fmu/tools/rms/update_petro_real.py
fmu/tools/rms/volumetrics.py
fmu/tools/rms/zone_mapping.py
fmu/tools/utilities/__init__.py
fmu/tools/utilities/sample_attributes.py
fmu_tools-1.26.0.dist-info/licenses/LICENSE
fmu_tools-1.26.0.dist-info/METADATA
fmu_tools-1.26.0.dist-info/WHEEL
fmu_tools-1.26.0.dist-info/entry_points.txt
fmu_tools-1.26.0.dist-info/top_level.txt
fmu_tools-1.26.0.dist-info/RECORD
