Metadata-Version: 2.4
Name: fmu-tools
Version: 1.26.0
Summary: Library for various tools and scripts within Fast Model Update
Author-email: Equinor <fg_fmu-atlas@equinor.com>
License:                    GNU LESSER GENERAL PUBLIC LICENSE
Project-URL: Homepage, https://github.com/equinor/fmu-tools
Project-URL: Repository, https://github.com/equinor/fmu-tools
Project-URL: Issues, https://github.com/equinor/fmu-tools/issues
Project-URL: Documentation, https://equinor.github.io/fmu-tools/
Keywords: energy,subsurface,reservoir,scientific,engineering
Classifier: Development Status :: 5 - Production/Stable
Classifier: Intended Audience :: Science/Research
Classifier: Topic :: Scientific/Engineering
Classifier: Topic :: Scientific/Engineering :: Physics
Classifier: Topic :: Software Development :: Libraries
Classifier: Topic :: Utilities
Classifier: Operating System :: POSIX :: Linux
Classifier: Programming Language :: Python :: 3.11
Classifier: Programming Language :: Python :: 3.12
Classifier: Programming Language :: Python :: 3.13
Classifier: Natural Language :: English
Classifier: License :: OSI Approved :: GNU Lesser General Public License v3 (LGPLv3)
Requires-Python: >=3.11
License-File: LICENSE
Requires-Dist: disjoint-set
Requires-Dist: jsonschema>=3.2.0
Requires-Dist: numpy>=1.23.5
Requires-Dist: openpyxl>=2.6
Requires-Dist: pandas>=0.21
Requires-Dist: pyyaml>=5.3
Requires-Dist: scipy>=1.2
Requires-Dist: xlrd>=1.2
Requires-Dist: xtgeo>=2.15
Provides-Extra: tests
Requires-Dist: mypy; extra == "tests"
Requires-Dist: ruff; extra == "tests"
Requires-Dist: pytest; extra == "tests"
Requires-Dist: pytest-cov; extra == "tests"
Requires-Dist: pytest-runner; extra == "tests"
Requires-Dist: pytest-xdist; extra == "tests"
Requires-Dist: pytest-mock; extra == "tests"
Requires-Dist: pytest-snapshot; extra == "tests"
Requires-Dist: rstcheck; extra == "tests"
Requires-Dist: types-PyYAML; extra == "tests"
Provides-Extra: docs
Requires-Dist: autoapi; extra == "docs"
Requires-Dist: myst-parser; extra == "docs"
Requires-Dist: sphinx<8.2.0; extra == "docs"
Requires-Dist: sphinx-argparse; extra == "docs"
Requires-Dist: sphinx-autodoc-typehints<2.4; extra == "docs"
Requires-Dist: sphinx-rtd-theme; extra == "docs"
Dynamic: license-file
